{
  "videos": [
    {
      "id": "7eX9Sa2zz0E"
    },
    {
      "id": "2XDcDNjBuYQ"
    },
    {
      "id": "EfMBXlDslys"
    },
    {
      "id": "I4pKVrHIhyc"
    },
    {
      "id": "6gaLZM4xLrM"
    },
    {
      "id": "G5GWsUwNqBs"
    },
    {
      "id": "HWo5YQoKz9Y"
    },
    {
      "id": "Rb6MguN0Uj4"
    },
    {
      "id": "SIif11QOsRI"
    },
    {
      "id": "QEAmTvan0EU"
    },
    {
      "id": "v876ZB75Jmc"
    },
    {
      "id": "XrenBOD0eX0"
    },
    {
      "id": "YbTFCh_XdYI"
    },
    {
      "id": "ewIj6BZ7qLg"
    },
    {
      "id": "0w404FmJr94"
    }
  ],

  "londontubevideos": [
    {
      "id": "1H7s7lJZC1I"
    },
    {
      "id": "XrenBOD0eX0"
    },
    {
      "id": "iBErp8qvWZg"
    },
    {
      "id": "9eczhuqEJgM"
    },
    {
      "id": "hatRy6e3xTM"
    },
    {
      "id": "eTMjxBpgn1E"
    },
    {
      "id": "StFAuGQf2mM"
    },
    {
      "id": "PRlzu4VWzZo"
    },
    {
      "id": "PTKlLYht2Jk"
    },
    {
      "id": "lxZwapLGKZU"
    },
    {
      "id": "EECy_-n-JKY"
    },
    {
      "id": "XrenBOD0eX0"
    },
    {
      "id": "YbTFCh_XdYI"
    },
    {
      "id": "ewIj6BZ7qLg"
    }
  ],

  "tubetopvideos": [
    {
      "id": "uiWVs1urXos"
    },
    {
      "id": "1G_w1Ir8JQg"
    },
    {
      "id": "LTDhbHM6Uqo"
    },
    {
      "id": "Bf8X2lADnoo"
    },
    {
      "id": "4vRplUf8KaU"
    },
    {
      "id": "NBS-S4krncg"
    },
    {
      "id": "f-P1AqGPULs"
    },
    {
      "id": "idK-amDKln0"
    },
    {
      "id": "fI7jQIPOW8I"
    }
  ]
}
